README.md
setup.py
codee/__init__.py
codee/__main__.py
codee/utils.py
codee.egg-info/PKG-INFO
codee.egg-info/SOURCES.txt
codee.egg-info/dependency_links.txt
codee.egg-info/entry_points.txt
codee.egg-info/not-zip-safe
codee.egg-info/top_level.txt