Metadata-Version: 2.1
Name: codee
Version: 0.0.1
Summary: Basic Utilities for Encoding and Decoding
Home-page: https://github.com/Ezharjan/codee
Author: Alexander Ezharjan
Author-email: mysoft@111.com
License: MIT
Platform: linux
Platform: windows
Platform: macos
Requires-Python: >=3.5
